{"stats":{"minecraft:picked_up":{"minecraft:repeater":5,"minecraft:redstone":7},"minecraft:custom":{"minecraft:open_barrel":80,"minecraft:time_since_rest":3698716,"minecraft:play_one_minute":3698716,"minecraft:crouch_one_cm":2056,"minecraft:sprint_one_cm":99388,"minecraft:walk_one_cm":241626,"minecraft:sneak_time":1605,"minecraft:jump":51,"minecraft:leave_game":17,"minecraft:time_since_death":3698716,"minecraft:fall_one_cm":9479,"minecraft:fly_one_cm":364541},"minecraft:used":{"minecraft:redstone_torch":4,"minecraft:item_frame":1,"minecraft:glass":22,"minecraft:lever":2,"minecraft:green_concrete":3,"minecraft:black_concrete":41,"minecraft:repeater":31,"minecraft:redstone_lamp":4,"minecraft:lime_concrete":4,"minecraft:command_block":5,"minecraft:iron_block":1,"minecraft:lime_wool":4,"minecraft:birch_sign":4,"minecraft:redstone":45,"minecraft:carrot_on_a_stick":84,"minecraft:bucket":2,"minecraft:bone_block":1,"minecraft:stone_button":3,"minecraft:quartz_block":2,"minecraft:white_glazed_terracotta":1,"minecraft:warped_button":2,"minecraft:crimson_planks":1,"minecraft:barrel":11}},"DataVersion":2580}